hopeit/app/__init__.py
hopeit/app/api.py
hopeit/app/client.py
hopeit/app/config.py
hopeit/app/context.py
hopeit/app/errors.py
hopeit/app/events.py
hopeit/app/logger.py
hopeit/app/py.typed
hopeit/cli/__init__.py
hopeit/cli/openapi.py
hopeit/cli/py.typed
hopeit/cli/server.py
hopeit/dataobjects/__init__.py
hopeit/dataobjects/payload.py
hopeit/dataobjects/py.typed
hopeit/server/__init__.py
hopeit/server/api.py
hopeit/server/collector.py
hopeit/server/compression.py
hopeit/server/config.py
hopeit/server/engine.py
hopeit/server/errors.py
hopeit/server/events.py
hopeit/server/imports.py
hopeit/server/logger.py
hopeit/server/metrics.py
hopeit/server/names.py
hopeit/server/py.typed
hopeit/server/runtime.py
hopeit/server/serialization.py
hopeit/server/steps.py
hopeit/server/version.py
hopeit/server/web.py
hopeit/server/wsgi.py
hopeit/streams/__init__.py
hopeit/streams/py.typed
hopeit/testing/__init__.py
hopeit/testing/apps.py
hopeit/testing/encryption.py
hopeit/testing/hooks.py
hopeit/testing/py.typed
hopeit/toolkit/__init__.py
hopeit/toolkit/auth.py
hopeit/toolkit/py.typed
hopeit/toolkit/web.py
hopeit_engine-0.28.1.dist-info/METADATA
hopeit_engine-0.28.1.dist-info/WHEEL
hopeit_engine-0.28.1.dist-info/entry_points.txt
hopeit_engine-0.28.1.dist-info/top_level.txt
hopeit_engine-0.28.1.dist-info/RECORD
