Metadata-Version: 2.4
Name: hopeit.engine
Version: 0.28.1
Summary: Hopeit Engine: Microservices with Streams
Author-email: Leo Smerling & Pablo Canto <contact@hopeit.com.ar>, Leo Smerling <contact@hopeit.com.ar>, Pablo Canto <contact@hopeit.com.ar>
License: Apache-2.0
Project-URL: Homepage, https://github.com/hopeit-git/hopeit.engine
Project-URL: CI: GitHub Actions, https://github.com/hopeit-git/hopeit.engine/actions?query=workflow
Project-URL: Docs: RTD, https://hopeitengine.readthedocs.io/en/latest/
Project-URL: GitHub: issues, https://github.com/hopeit-git/hopeit.engine/issues
Project-URL: GitHub: repo, https://github.com/hopeit-git/hopeit.engine
Classifier: Intended Audience :: Developers
Classifier: Programming Language :: Python
Classifier: Programming Language :: Python :: 3.10
Classifier: Programming Language :: Python :: 3.11
Classifier: Programming Language :: Python :: 3.12
Classifier: Programming Language :: Python :: 3.13
Classifier: Programming Language :: Python :: 3.14
Classifier: Development Status :: 5 - Production/Stable
Classifier: Operating System :: POSIX :: Linux
Classifier: Operating System :: MacOS :: MacOS X
Classifier: Operating System :: Microsoft :: Windows
Classifier: Topic :: Internet :: WWW/HTTP
Classifier: Topic :: Software Development :: Libraries :: Python Modules
Classifier: Framework :: AsyncIO
Requires-Dist: pydantic<3,>=2.12.5
Requires-Dist: lz4>=4.4.5
Requires-Dist: PyJWT[crypto]>=2.10.1
Requires-Dist: deepdiff>=8.6.1
Requires-Dist: multidict>=6.7.0
Requires-Dist: aiohttp<4,>=3.11.12
Requires-Dist: aiohttp-cors>=0.8.1
Requires-Dist: aiohttp-swagger3>=0.10.0
Requires-Dist: gunicorn>=23.0.0
Requires-Dist: click>=8.3.1
Requires-Dist: uvloop>=0.22; platform_system != "Windows"
Provides-Extra: web
Provides-Extra: cli
Provides-Extra: redis-streams
Requires-Dist: hopeit.redis-streams==0.28.1; extra == "redis-streams"
Provides-Extra: redis-storage
Requires-Dist: hopeit.redis-storage==0.28.1; extra == "redis-storage"
Provides-Extra: fs-storage
Requires-Dist: hopeit.fs-storage==0.28.1; extra == "fs-storage"
Provides-Extra: config-manager
Requires-Dist: hopeit.config-manager==0.28.1; extra == "config-manager"
Provides-Extra: log-streamer
Requires-Dist: hopeit.log-streamer==0.28.1; extra == "log-streamer"
Provides-Extra: apps-visualizer
Requires-Dist: hopeit.apps-visualizer==0.28.1; extra == "apps-visualizer"
Provides-Extra: apps-client
Requires-Dist: hopeit.apps-client==0.28.1; extra == "apps-client"
Provides-Extra: dataframes
Requires-Dist: hopeit.dataframes==0.28.1; extra == "dataframes"
